pepperpy_core/__init__.py
pepperpy_core/cache.py
pepperpy_core/config.py
pepperpy_core/context.py
pepperpy_core/dev.py
pepperpy_core/event.py
pepperpy_core/exceptions.py
pepperpy_core/handlers.pyi
pepperpy_core/io.py
pepperpy_core/logging.py
pepperpy_core/main.py
pepperpy_core/middleware.pyi
pepperpy_core/module.py
pepperpy_core/network.py
pepperpy_core/pipeline.py
pepperpy_core/plugin.py
pepperpy_core/py.typed
pepperpy_core/registry.py
pepperpy_core/resources.py
pepperpy_core/security.py
pepperpy_core/serialization.py
pepperpy_core/task.py
pepperpy_core/telemetry.py
pepperpy_core/types.py
pepperpy_core/utils.py
pepperpy_core/validators.py
pepperpy_core-3.1.1.dist-info/LICENSE
pepperpy_core-3.1.1.dist-info/METADATA
pepperpy_core-3.1.1.dist-info/WHEEL
pepperpy_core-3.1.1.dist-info/entry_points.txt
pepperpy_core-3.1.1.dist-info/RECORD
